game_of_life_tui/__init__.py
game_of_life_tui/__main__.py
game_of_life_tui/app.py
game_of_life_tui/game.py
game_of_life_tui/patterns.py
game_of_life_tui-1.2.0.dist-info/licenses/LICENSE
game_of_life_tui-1.2.0.dist-info/METADATA
game_of_life_tui-1.2.0.dist-info/WHEEL
game_of_life_tui-1.2.0.dist-info/entry_points.txt
game_of_life_tui-1.2.0.dist-info/top_level.txt
game_of_life_tui-1.2.0.dist-info/RECORD
