Metadata-Version: 2.4
Name: game-of-life-tui
Version: 1.2.0
Summary: Conway's Game of Life in your terminal with an interactive TUI
Author: Joseph Volmer
License: MIT
Project-URL: Homepage, https://github.com/josephvolmer/game-of-life-tui
Project-URL: Repository, https://github.com/josephvolmer/game-of-life-tui
Project-URL: Issues, https://github.com/josephvolmer/game-of-life-tui/issues
Keywords: game,game-of-life,cellular-automaton,tui,terminal,textual
Classifier: Development Status :: 4 - Beta
Classifier: Environment :: Console
Classifier: Intended Audience :: End Users/Desktop
Classifier: Intended Audience :: Education
Classifier: License :: OSI Approved :: MIT License
Classifier: Operating System :: OS Independent
Classifier: Programming Language :: Python :: 3
Classifier: Programming Language :: Python :: 3.8
Classifier: Programming Language :: Python :: 3.9
Classifier: Programming Language :: Python :: 3.10
Classifier: Programming Language :: Python :: 3.11
Classifier: Programming Language :: Python :: 3.12
Classifier: Topic :: Games/Entertainment :: Simulation
Requires-Python: >=3.8
License-File: LICENSE
Requires-Dist: textual>=0.47.0
Requires-Dist: rich<14.0.0,>=13.0.0
Dynamic: license-file
